altair_transform/__init__.py
altair_transform/core.py
altair_transform/extract.py
altair_transform/vegaexpr.py
altair_transform/tests/README.md
altair_transform/tests/__init__.py
altair_transform/tests/test_core.py
altair_transform/tests/test_examples.py
altair_transform/tests/test_extract.py
altair_transform/tests/test_vegaexpr.py
altair_transform/transform/__init__.py
altair_transform/transform/aggregate.py
altair_transform/transform/bin.py
altair_transform/transform/calculate.py
altair_transform/transform/filter.py
altair_transform/transform/flatten.py
altair_transform/transform/fold.py
altair_transform/transform/impute.py
altair_transform/transform/joinaggregate.py
altair_transform/transform/lookup.py
altair_transform/transform/sample.py
altair_transform/transform/timeunit.py
altair_transform/transform/visitor.py
altair_transform/transform/window.py
altair_transform/transform/tests/__init__.py
altair_transform/transform/tests/test_transform.py
altair_transform/utils/__init__.py
altair_transform/utils/_evaljs.py
altair_transform/utils/_parser.py
altair_transform/utils/_parser_Parser_parsetab.py
altair_transform/utils/ast.py
altair_transform/utils/data.py
altair_transform/utils/timeunit.py
altair_transform/utils/tests/__init__.py
altair_transform/utils/tests/_testcases.py
altair_transform/utils/tests/test_data.py
altair_transform/utils/tests/test_evaljs.py
altair_transform/utils/tests/test_parser.py
altair_transform/utils/tests/test_timeunit.py
altair_transform-0.2.0.dist-info/LICENSE
altair_transform-0.2.0.dist-info/METADATA
altair_transform-0.2.0.dist-info/WHEEL
altair_transform-0.2.0.dist-info/top_level.txt
altair_transform-0.2.0.dist-info/RECORD
