Metadata-Version: 2.1
Name: altair_transform
Version: 0.2.0
Summary: A python engine for evaluating Altair transforms.
Home-page: http://github.com/altair-viz/altair-transform/
Author: Jake VanderPlas
Author-email: jakevdp@gmail.com
License: MIT
Download-URL: http://github.com/altair-viz/altair-transform/
Platform: UNKNOWN
Classifier: Environment :: Console
Classifier: Intended Audience :: Science/Research
Classifier: License :: OSI Approved :: MIT License
Classifier: Natural Language :: English
Classifier: Programming Language :: Python :: 3.6
Classifier: Programming Language :: Python :: 3.7
Classifier: Programming Language :: Python :: 3.8
Requires-Python: >=3.6
